LICENSE.txt
MANIFEST.in
README.md
pyproject.toml
setup.cfg
setup.py
Utils4R/__init__.py
Utils4R/basic.py
Utils4R/request.py
Utils4R.egg-info/PKG-INFO
Utils4R.egg-info/SOURCES.txt
Utils4R.egg-info/dependency_links.txt
Utils4R.egg-info/requires.txt
Utils4R.egg-info/top_level.txt
Utils4R/_utils_abc/__init__.py
Utils4R/_utils_abc/spider.py
Utils4R/db/__init__.py
Utils4R/db/mysql.py
Utils4R/extract/__init__.py
Utils4R/extract/string.py
Utils4R/io/__init__.py
Utils4R/io/file.py
Utils4R/io/json.py
Utils4R/io/mysql.py
Utils4R/static/__init__.py
Utils4R/static/user_agent.py