Metadata-Version: 2.1
Name: Utils4R
Version: 0.0.18
Summary: Utils for Researcher
Home-page: https://github.com/ChangxingJiang/Utils4R
Author: ChangXing
Author-email: 1278729001@qq.com
License: UNKNOWN
Platform: UNKNOWN
Classifier: Development Status :: 3 - Alpha
Classifier: License :: OSI Approved :: MIT License
Classifier: Programming Language :: Python :: 3.8
Classifier: Programming Language :: Python
